Workbook

Sheet Bookings
A1: Month | B1: Platform | C1: Guest Name | D1: Check-In | E1: Check-Out | F1: Nights | G1: Nightly Rate | H1: Cleaning Fee | I1: Gross Revenue | J1: Platform Fees | K1: Net Payout | L1: Notes
A2: Mar 2026 | B2: VRBO | I2: 298.42 | K2: 298.42 | L2: Payout amount from VRBO — booking details TBD
A3: Apr 2026 | B3: Airbnb | C3: Tyler Nicholson | D3: 46114 | E3: 46118 | F3: 4 | G3: 127.32 | H3: 75 | I3: 609.27 | J3: 18.3 | K3: 590.97 | L3: Airbnb HMTK9FNMQK | Pet fee: $25.00 | Tax remitted: $40.05
A4: Apr 2026 | B4: Airbnb | C4: Kepi Garner Jr | D4: 46118 | E4: 46120 | F4: 2 | G4: 124.81 | H4: 75 | I4: 324.61 | J4: 9.75 | K4: 314.86 | L4: Airbnb HMRWNBH82B | Tax remitted: $21.34
A5: Apr 2026 | B5: Airbnb | C5: Dalyce Sellers | D5: 46122 | E5: 46126 | F5: 4 | G5: 105.2 | I5: 420.8 | J5: 12.62 | K5: 408.18 | L5: Airbnb HM4MWDKA2D | Tax remitted: $25.25
A6: April 2026 | B6: Direct (Zelle) | C6: Noah Parrish group (McMeen/Parrish/Armstrong/Stevens) | F6: 105 | G6: 0 | H6: 0 | I6: 1051.5 | J6: Active | K6: 105-day rental. 4 tenants: Robert McMeen $262.50, Noah Parrish $263, Dylan Armstrong $263, Carson Stevens $263. Payments received 04/07/2026.

Sheet Expenses
A1: Date | B1: Month | C1: Category | D1: Vendor/Payee | E1: Description | F1: Amount | G1: Payment Method | H1: Receipt? (Y/N) | I1: Status
A2: 46111 | B2: =IF(A2="","",TEXT(A2,"MMM YYYY")) | C2: Cleaning & turnover | D2: Julie Rose | E2: Airbnb turnover cleaning | F2: 50 | G2: Cash | H2: N | I2: Business
A3: 46118 | B3: =IF(A3="","",TEXT(A3,"MMM YYYY")) | C3: Cleaning & turnover | D3: Julie Rose | E3: Airbnb turnover cleaning | F3: 60 | G3: Cash | H3: N | I3: Business
A4: 46120 | B4: =IF(A4="","",TEXT(A4,"MMM YYYY")) | C4: Cleaning & turnover | D4: Julie Rose | E4: Airbnb turnover cleaning | F4: 60 | G4: Cash | H4: N | I4: Business
A5: 46023 | B5: =IF(A5="","",TEXT(A5,"MMM YYYY")) | C5: Repairs & maintenance | D5: Lowe's | E5: LOWES #00907* 866-483-7521 NC | Dishwasher | F5: 323.67 | G5: Robinhood CC | H5: CC | I5: Business
A6: 46023 | B6: =IF(A6="","",TEXT(A6,"MMM YYYY")) | C6: Supplies | D6: Brookshire Brothers | E6: BROOKSHIRE BROS #10 FAIRFIELD TX | Property supplies | F6: 12.06 | G6: Robinhood CC | H6: CC | I6: Business
A7: 46025 | B7: =IF(A7="","",TEXT(A7,"MMM YYYY")) | C7: Supplies | D7: Dfw Estate Liquidators | E7: DFW ESTATE LIQUIDATORS WEATHERFORD TX | Furnishing | F7: 48.46 | G7: Robinhood CC | H7: CC | I7: Business
A8: 46025 | B8: =IF(A8="","",TEXT(A8,"MMM YYYY")) | C8: Supplies | D8: Dfw Estate Liquidators | E8: DFW ESTATE LIQUIDATORS WEATHERFORD TX | Furnishing | F8: 8.4 | G8: Robinhood CC | H8: CC | I8: Business
A9: 46026 | B9: =IF(A9="","",TEXT(A9,"MMM YYYY")) | C9: Repairs & maintenance | D9: Refund: Home Depot | E9: REFUND: THE HOME DEPOT #8517 GRAND PRAIRIETX | VERIFY: GP/Mansfield HD - STR or personal? | F9: -20.92 | G9: Robinhood CC | H9: CC | I9: Review
A10: 46026 | B10: =IF(A10="","",TEXT(A10,"MMM YYYY")) | C10: Repairs & maintenance | D10: Refund: Home Depot | E10: REFUND: THE HOME DEPOT #8517 GRAND PRAIRIETX | VERIFY: GP/Mansfield HD - STR or personal? | F10: -17.47 | G10: Robinhood CC | H10: CC | I10: Review
A11: 46027 | B11: =IF(A11="","",TEXT(A11,"MMM YYYY")) | C11: Repairs & maintenance | D11: Home Depot | E11: THE HOME DEPOT #6817 CORSICANA TX | F11: 269.82 | G11: Robinhood CC | H11: CC | I11: Business
A12: 46028 | B12: =IF(A12="","",TEXT(A12,"MMM YYYY")) | C12: Utilities | D12: Maga Waste, Llc | E12: TRB MAGA WASTE LLC 802-5603595 VT | Trash service | F12: 170 | G12: Robinhood CC | H12: CC | I12: Business
A13: 46029 | B13: =IF(A13="","",TEXT(A13,"MMM YYYY")) | C13: Repairs & maintenance | D13: Home Depot | E13: THE HOME DEPOT #6568 MANSFIELD TX | VERIFY: GP/Mansfield HD - STR or personal? | F13: 142.7 | G13: Robinhood CC | H13: CC | I13: Review
... A70: 46118 | B70: =IF(A70="","",TEXT(A70,"MMM YYYY")) | C70: Repairs & maintenance | D70: Home Depot | E70: THE HOME DEPOT #8517 GRAND PRAIRIETX | VERIFY: GP/Mansfield HD - STR or personal? | F70: 69.75 | G70: Robinhood CC | H70: CC | I70: Review
A71: 46007 | B71: December 2025 | C71: Repairs & maintenance | D71: Jeff Yancey | E71: Contractor - property work (Fairfield) | F71: 510 | G71: Zelle (6113) | H71: CC | I71: Business
A72: 46015 | B72: December 2025 | C72: Repairs & maintenance | D72: Jeff Yancey | E72: Contractor - property work (Fairfield) | F72: 700 | G72: Zelle (6113) | H72: CC | I72: Business
A73: 46034 | B73: January 2026 | C73: Repairs & maintenance | D73: Jeff Yancey | E73: Contractor - property work (Fairfield) | F73: 775 | G73: Zelle (6113) | H73: CC | I73: Business
A74: 46062 | B74: February 2026 | C74: Repairs & maintenance | D74: Jerry Yancey | E74: Contractor - property work (Fairfield) | F74: 1833.33 | G74: Zelle (6113) | H74: CC | I74: Business
A75: 46087 | B75: March 2026 | C75: Repairs & maintenance | D75: Jerry Yancey | E75: Contractor - small payment | F75: 6.82 | G75: Zelle (6113) | H75: CC | I75: Business
A76: 46034 | B76: January 2026 | C76: Repairs & maintenance | D76: Jacob Hance | E76: Contractor - property work | F76: 150 | G76: Zelle (6113) | H76: CC | I76: Business
A77: 46034 | B77: January 2026 | C77: Repairs & maintenance | D77: Jacob Hance | E77: Contractor - property work | F77: 255 | G77: Zelle (6113) | H77: CC | I77: Business
A78: 46034 | B78: January 2026 | C78: Repairs & maintenance | D78: Jacob Hance | E78: Contractor - property work | F78: 40 | G78: Zelle (6113) | H78: CC | I78: Business
A79: 46036 | B79: January 2026 | C79: Repairs & maintenance | D79: Jacob Hance | E79: Contractor - property work | F79: 800 | G79: Zelle (6113) | H79: CC | I79: Business
A80: 46042 | B80: January 2026 | C80: Repairs & maintenance | D80: Jacob Hance | E80: Contractor - property work | F80: 801 | G80: Zelle (6113) | H80: CC | I80: Business
A81: 46042 | B81: January 2026 | C81: Repairs & maintenance | D81: Jacob Hance | E81: Contractor - property work | F81: 60 | G81: Zelle (6113) | H81: CC | I81: Business
A82: 46042 | B82: January 2026 | C82: Repairs & maintenance | D82: Jacob Hance | E82: Contractor - property work | F82: 25 | G82: Zelle (6113) | H82: CC | I82: Business
... A136: 45985 | B136: November 2025 | C136: Other | D136: Unaccounted Cash | E136: Remaining from $7,500 cash withdrawal — INVESTIGATE: $1,200 Jeff + $2,400 carts + $500 ATM = $4,100 accounted. This $3,400 is unaccounted. Do NOT report until documented. | F136: 3400 | G136: Cash | H136: N | I136: Review
B137: =IF(A137="","",TEXT(A137,"MMM YYYY"))
B138: =IF(A138="","",TEXT(A138,"MMM YYYY"))
B139: =IF(A139="","",TEXT(A139,"MMM YYYY"))
B140: =IF(A140="","",TEXT(A140,"MMM YYYY"))
B141: =IF(A141="","",TEXT(A141,"MMM YYYY"))
B142: =IF(A142="","",TEXT(A142,"MMM YYYY"))
B143: =IF(A143="","",TEXT(A143,"MMM YYYY"))
B144: =IF(A144="","",TEXT(A144,"MMM YYYY"))
B145: =IF(A145="","",TEXT(A145,"MMM YYYY"))
B146: =IF(A146="","",TEXT(A146,"MMM YYYY"))
B147: =IF(A147="","",TEXT(A147,"MMM YYYY"))
B148: =IF(A148="","",TEXT(A148,"MMM YYYY"))
... B201: =IF(A201="","",TEXT(A201,"MMM YYYY"))

Sheet Monthly Summary
A1: Keng's Landing — Monthly P&L Summary
A3: Month | B3: Revenue | C3: Expenses | D3: Net Profit/Loss | E3: Bookings | F3: Nights Booked | G3: Occupancy Rate
A4: Jan 2026 | B4: =SUMIFS(Bookings!$K$2:$K$101,Bookings!$A$2:$A$101,A4) | C4: =SUMIFS(Expenses!$F$2:$F$201,Expenses!$B$2:$B$201,A4) | D4: =B4-C4 | E4: =COUNTIFS(Bookings!$A$2:$A$101,A4) | F4: =SUMIFS(Bookings!$F$2:$F$101,Bookings!$A$2:$A$101,A4) | G4: =IFERROR(F4/31,0)
A5: Feb 2026 | B5: =SUMIFS(Bookings!$K$2:$K$101,Bookings!$A$2:$A$101,A5) | C5: =SUMIFS(Expenses!$F$2:$F$201,Expenses!$B$2:$B$201,A5) | D5: =B5-C5 | E5: =COUNTIFS(Bookings!$A$2:$A$101,A5) | F5: =SUMIFS(Bookings!$F$2:$F$101,Bookings!$A$2:$A$101,A5) | G5: =IFERROR(F5/28,0)
A6: Mar 2026 | B6: =SUMIFS(Bookings!$K$2:$K$101,Bookings!$A$2:$A$101,A6) | C6: =SUMIFS(Expenses!$F$2:$F$201,Expenses!$B$2:$B$201,A6) | D6: =B6-C6 | E6: =COUNTIFS(Bookings!$A$2:$A$101,A6) | F6: =SUMIFS(Bookings!$F$2:$F$101,Bookings!$A$2:$A$101,A6) | G6: =IFERROR(F6/31,0)
A7: Apr 2026 | B7: =SUMIFS(Bookings!$K$2:$K$101,Bookings!$A$2:$A$101,A7) | C7: =SUMIFS(Expenses!$F$2:$F$201,Expenses!$B$2:$B$201,A7) | D7: =B7-C7 | E7: =COUNTIFS(Bookings!$A$2:$A$101,A7) | F7: =SUMIFS(Bookings!$F$2:$F$101,Bookings!$A$2:$A$101,A7) | G7: =IFERROR(F7/30,0)
A8: May 2026 | B8: =SUMIFS(Bookings!$K$2:$K$101,Bookings!$A$2:$A$101,A8) | C8: =SUMIFS(Expenses!$F$2:$F$201,Expenses!$B$2:$B$201,A8) | D8: =B8-C8 | E8: =COUNTIFS(Bookings!$A$2:$A$101,A8) | F8: =SUMIFS(Bookings!$F$2:$F$101,Bookings!$A$2:$A$101,A8) | G8: =IFERROR(F8/31,0)
A9: Jun 2026 | B9: =SUMIFS(Bookings!$K$2:$K$101,Bookings!$A$2:$A$101,A9) | C9: =SUMIFS(Expenses!$F$2:$F$201,Expenses!$B$2:$B$201,A9) | D9: =B9-C9 | E9: =COUNTIFS(Bookings!$A$2:$A$101,A9) | F9: =SUMIFS(Bookings!$F$2:$F$101,Bookings!$A$2:$A$101,A9) | G9: =IFERROR(F9/30,0)
A10: Jul 2026 | B10: =SUMIFS(Bookings!$K$2:$K$101,Bookings!$A$2:$A$101,A10) | C10: =SUMIFS(Expenses!$F$2:$F$201,Expenses!$B$2:$B$201,A10) | D10: =B10-C10 | E10: =COUNTIFS(Bookings!$A$2:$A$101,A10) | F10: =SUMIFS(Bookings!$F$2:$F$101,Bookings!$A$2:$A$101,A10) | G10: =IFERROR(F10/31,0)
A11: Aug 2026 | B11: =SUMIFS(Bookings!$K$2:$K$101,Bookings!$A$2:$A$101,A11) | C11: =SUMIFS(Expenses!$F$2:$F$201,Expenses!$B$2:$B$201,A11) | D11: =B11-C11 | E11: =COUNTIFS(Bookings!$A$2:$A$101,A11) | F11: =SUMIFS(Bookings!$F$2:$F$101,Bookings!$A$2:$A$101,A11) | G11: =IFERROR(F11/31,0)
A12: Sep 2026 | B12: =SUMIFS(Bookings!$K$2:$K$101,Bookings!$A$2:$A$101,A12) | C12: =SUMIFS(Expenses!$F$2:$F$201,Expenses!$B$2:$B$201,A12) | D12: =B12-C12 | E12: =COUNTIFS(Bookings!$A$2:$A$101,A12) | F12: =SUMIFS(Bookings!$F$2:$F$101,Bookings!$A$2:$A$101,A12) | G12: =IFERROR(F12/30,0)
A13: Oct 2026 | B13: =SUMIFS(Bookings!$K$2:$K$101,Bookings!$A$2:$A$101,A13) | C13: =SUMIFS(Expenses!$F$2:$F$201,Expenses!$B$2:$B$201,A13) | D13: =B13-C13 | E13: =COUNTIFS(Bookings!$A$2:$A$101,A13) | F13: =SUMIFS(Bookings!$F$2:$F$101,Bookings!$A$2:$A$101,A13) | G13: =IFERROR(F13/31,0)
A14: Nov 2026 | B14: =SUMIFS(Bookings!$K$2:$K$101,Bookings!$A$2:$A$101,A14) | C14: =SUMIFS(Expenses!$F$2:$F$201,Expenses!$B$2:$B$201,A14) | D14: =B14-C14 | E14: =COUNTIFS(Bookings!$A$2:$A$101,A14) | F14: =SUMIFS(Bookings!$F$2:$F$101,Bookings!$A$2:$A$101,A14) | G14: =IFERROR(F14/30,0)
A15: Dec 2026 | B15: =SUMIFS(Bookings!$K$2:$K$101,Bookings!$A$2:$A$101,A15) | C15: =SUMIFS(Expenses!$F$2:$F$201,Expenses!$B$2:$B$201,A15) | D15: =B15-C15 | E15: =COUNTIFS(Bookings!$A$2:$A$101,A15) | F15: =SUMIFS(Bookings!$F$2:$F$101,Bookings!$A$2:$A$101,A15) | G15: =IFERROR(F15/31,0)
A16: TOTAL 2026 | B16: =SUM(B4:B15) | C16: =SUM(C4:C15) | D16: =SUM(D4:D15) | E16: =SUM(E4:E15) | F16: =SUM(F4:F15) | G16: =IFERROR(F16/365,0)
A18: Expense Breakdown by Category
A19: Category | B19: YTD Total | C19: % of Total
A20: Mortgage Interest | B20: =SUMIFS(Expenses!$F$2:$F$201,Expenses!$C$2:$C$201,A20) | C20: =IFERROR(B20/C16,0)
A21: Property Taxes | B21: =SUMIFS(Expenses!$F$2:$F$201,Expenses!$C$2:$C$201,A21) | C21: =IFERROR(B21/C16,0)
A22: Insurance | B22: =SUMIFS(Expenses!$F$2:$F$201,Expenses!$C$2:$C$201,A22) | C22: =IFERROR(B22/C16,0)
A23: Repairs & Maintenance | B23: =SUMIFS(Expenses!$F$2:$F$201,Expenses!$C$2:$C$201,A23) | C23: =IFERROR(B23/C16,0)
A24: Supplies | B24: =SUMIFS(Expenses!$F$2:$F$201,Expenses!$C$2:$C$201,A24) | C24: =IFERROR(B24/C16,0)
A25: Utilities | B25: =SUMIFS(Expenses!$F$2:$F$201,Expenses!$C$2:$C$201,A25) | C25: =IFERROR(B25/C16,0)
A26: Cleaning & Turnover | B26: =SUMIFS(Expenses!$F$2:$F$201,Expenses!$C$2:$C$201,A26) | C26: =IFERROR(B26/C16,0)
A27: Platform Fees | B27: =SUMIFS(Expenses!$F$2:$F$201,Expenses!$C$2:$C$201,A27) | C27: =IFERROR(B27/C16,0)
A28: Professional Services | B28: =SUMIFS(Expenses!$F$2:$F$201,Expenses!$C$2:$C$201,A28) | C28: =IFERROR(B28/C16,0)
A29: Advertising | B29: =SUMIFS(Expenses!$F$2:$F$201,Expenses!$C$2:$C$201,A29) | C29: =IFERROR(B29/C16,0)
A30: Travel / Mileage | B30: =SUMIFS(Expenses!$F$2:$F$201,Expenses!$C$2:$C$201,A30) | C30: =IFERROR(B30/C16,0)
A31: Depreciation | B31: =SUMIFS(Expenses!$F$2:$F$201,Expenses!$C$2:$C$201,A31) | C31: =IFERROR(B31/C16,0)
A32: Other | B32: =SUMIFS(Expenses!$F$2:$F$201,Expenses!$C$2:$C$201,A32) | C32: =IFERROR(B32/C16,0)
A33: Total | B33: =SUM(B20:B32)

Sheet Investment & ROI
A1: Keng's Landing — Investment Recovery Tracker
A3: INITIAL INVESTMENT
A4: Property Purchase (4 acres + house, hot tub, pond) | B4: 87000
A5: Improvements | B5: 0
A6: Total Investment | B6: =B4+B5
A8: ROI TARGET
A9: Target payback (years) | B9: 7
A10: Required annual net profit | B10: =B6/B9
A11: Required monthly net profit | B11: =B10/12
A12: At $150/night, min nights/month needed | B12: =ROUNDUP(B11/150,0)
A14: PROGRESS (auto-calculated)
A15: Total revenue to date | B15: ='Monthly Summary'!B16
A16: Total expenses to date | B16: ='Monthly Summary'!C16
A17: Net profit to date | B17: ='Monthly Summary'!D16
A18: Remaining to recover | B18: =B6-B17
A19: % recovered | B19: =IFERROR(B17/B6,0)
A20: Total bookings to date | B20: ='Monthly Summary'!E16
A21: Annual occupancy rate | B21: ='Monthly Summary'!G16
A23: PACE PROJECTIONS
A24: Months with revenue | B24: =COUNTIF('Monthly Summary'!B4:B15,">0")
A25: Average monthly net profit | B25: =IFERROR(B17/B24,0)
A26: Projected annual net profit (at current pace) | B26: =B25*12
A27: Projected years to recover investment | B27: =IFERROR(B6/B26,0)
A28: On track for 7-year target? | B28: =IF(B24=0,"No data yet",IF(B27<=B9,"YES","NO — need more revenue"))
A30: FUTURE EXPANSION NOTES
A31: • Tiny homes / mobile homes — additional rental units on the 4 acres
A32: • Infrastructure needed: gravel paths, septic, water, electric meter
A33: • May be tracked as separate venture/series — TBD with CPA
A34: • Julie Rose exploring property management role ($20/hr)

Sheet Budget vs Actual
A1: Keng's Landing — Annual Budget vs Actual
A2: Set your Annual Budget per category in column B. Everything else auto-calculates.
A4: Category | B4: Annual Budget | C4: Monthly Budget | D4: YTD Actual | E4: YTD Variance | F4: % Used
A5: Mortgage Interest | C5: =IFERROR(B5/12,0) | D5: =SUMIFS(Expenses!$F$2:$F$201,Expenses!$C$2:$C$201,A5) | E5: =B5-D5 | F5: =IFERROR(D5/B5,0)
A6: Property Taxes | C6: =IFERROR(B6/12,0) | D6: =SUMIFS(Expenses!$F$2:$F$201,Expenses!$C$2:$C$201,A6) | E6: =B6-D6 | F6: =IFERROR(D6/B6,0)
A7: Insurance | C7: =IFERROR(B7/12,0) | D7: =SUMIFS(Expenses!$F$2:$F$201,Expenses!$C$2:$C$201,A7) | E7: =B7-D7 | F7: =IFERROR(D7/B7,0)
A8: Repairs & Maintenance | C8: =IFERROR(B8/12,0) | D8: =SUMIFS(Expenses!$F$2:$F$201,Expenses!$C$2:$C$201,A8) | E8: =B8-D8 | F8: =IFERROR(D8/B8,0)
A9: Supplies | C9: =IFERROR(B9/12,0) | D9: =SUMIFS(Expenses!$F$2:$F$201,Expenses!$C$2:$C$201,A9) | E9: =B9-D9 | F9: =IFERROR(D9/B9,0)
A10: Utilities | C10: =IFERROR(B10/12,0) | D10: =SUMIFS(Expenses!$F$2:$F$201,Expenses!$C$2:$C$201,A10) | E10: =B10-D10 | F10: =IFERROR(D10/B10,0)
A11: Cleaning & Turnover | C11: =IFERROR(B11/12,0) | D11: =SUMIFS(Expenses!$F$2:$F$201,Expenses!$C$2:$C$201,A11) | E11: =B11-D11 | F11: =IFERROR(D11/B11,0)
A12: Platform Fees | C12: =IFERROR(B12/12,0) | D12: =SUMIFS(Expenses!$F$2:$F$201,Expenses!$C$2:$C$201,A12) | E12: =B12-D12 | F12: =IFERROR(D12/B12,0)
A13: Professional Services | C13: =IFERROR(B13/12,0) | D13: =SUMIFS(Expenses!$F$2:$F$201,Expenses!$C$2:$C$201,A13) | E13: =B13-D13 | F13: =IFERROR(D13/B13,0)
A14: Advertising | C14: =IFERROR(B14/12,0) | D14: =SUMIFS(Expenses!$F$2:$F$201,Expenses!$C$2:$C$201,A14) | E14: =B14-D14 | F14: =IFERROR(D14/B14,0)
A15: Travel / Mileage | C15: =IFERROR(B15/12,0) | D15: =SUMIFS(Expenses!$F$2:$F$201,Expenses!$C$2:$C$201,A15) | E15: =B15-D15 | F15: =IFERROR(D15/B15,0)
A16: Depreciation | C16: =IFERROR(B16/12,0) | D16: =SUMIFS(Expenses!$F$2:$F$201,Expenses!$C$2:$C$201,A16) | E16: =B16-D16 | F16: =IFERROR(D16/B16,0)
A17: Other | C17: =IFERROR(B17/12,0) | D17: =SUMIFS(Expenses!$F$2:$F$201,Expenses!$C$2:$C$201,A17) | E17: =B17-D17 | F17: =IFERROR(D17/B17,0)
A18: TOTAL | B18: =SUM(B5:B17) | C18: =SUM(C5:C17) | D18: =SUM(D5:D17) | E18: =SUM(E5:E17) | F18: =IFERROR(D18/B18,0)
A20: Revenue Target
A21: Metric | B21: Annual Target | C21: Monthly Target | D21: YTD Actual | E21: YTD Variance | F21: % Achieved
A22: Gross Revenue | C22: =IFERROR(B22/12,0) | D22: ='Monthly Summary'!B16 | E22: =D22-B22 | F22: =IFERROR(D22/B22,0)
A23: Net Profit | C23: =IFERROR(B23/12,0) | D23: ='Monthly Summary'!D16 | E23: =D23-B23 | F23: =IFERROR(D23/B23,0)

Sheet Category Reference
A1: Schedule E Expense Categories — Quick Reference
A3: Category | B3: What Counts | C3: Examples
A4: Mortgage Interest | B4: Interest portion of monthly mortgage only | C4: Bank statement line item
A5: Property Taxes | B5: County/city property taxes | C5: Freestone County tax bill
A6: Insurance | B6: Property insurance premiums | C6: Landlord policy, umbrella policy
A7: Repairs & Maintenance | B7: Fixing or maintaining existing property | C7: Plumbing, HVAC repair, pest control, hot tub maintenance
A8: Supplies | B8: Consumables for guests or property | C8: Cleaning supplies, toiletries, linens, kitchen items, light bulbs
A9: Utilities | B9: Monthly service bills | C9: Electric, water, propane, Starlink internet, trash
A10: Cleaning & Turnover | B10: Cleaning between guests | C10: Professional cleaner per-visit fee (Julie Rose)
A11: Platform Fees | B11: Host fees charged by platforms | C11: Airbnb 3% host fee (if separate from payout)
A12: Professional Services | B12: Expert help | C12: CPA, attorney, property manager
A13: Advertising | B13: Marketing spend | C13: Listing boost, professional photos
A14: Travel / Mileage | B14: Trips to property for business | C14: IRS standard mileage rate x miles driven
... A16: Other | B16: Anything that doesn't fit above | C16: Smart locks, permits, software subscriptions

Sheet Mileage Log
A1: Date | B1: Origin | C1: Destination | D1: Round Trip Miles | E1: Purpose | F1: Stops/Evidence | G1: IRS Rate | H1: Deduction
A2: 46023 | B2: Mansfield, TX | C2: 360 County Road, Fairfield, TX | D2: 120 | E2: property work, supplies | F2: Brookshire Brothers, McDonald’s | G2: 0.7 | H2: 84
A3: 46027 | B3: Mansfield, TX | C3: 360 County Road, Fairfield, TX | D3: 120 | E3: maintenance/repairs | F3: Home Depot | G3: 0.7 | H3: 84
A4: 46031 | B4: Mansfield, TX | C4: 360 County Road, Fairfield, TX | D4: 120 | E4: maintenance/repairs, property work, supplies | F4: Burger King, Brookshire Brothers, Home Depot | G4: 0.7 | H4: 84
A5: 46032 | B5: Mansfield, TX | C5: 360 County Road, Fairfield, TX | D5: 120 | E5: maintenance/repairs | F5: Home Depot | G5: 0.7 | H5: 84
A6: 46034 | B6: Mansfield, TX | C6: 360 County Road, Fairfield, TX | D6: 120 | E6: maintenance/repairs | F6: Refund: Home Depot | G6: 0.7 | H6: 84
A7: 46037 | B7: Mansfield, TX | C7: 360 County Road, Fairfield, TX | D7: 120 | E7: maintenance/repairs | F7: Brenco, Home Depot | G7: 0.7 | H7: 84
A8: 46038 | B8: Mansfield, TX | C8: 360 County Road, Fairfield, TX | D8: 120 | E8: maintenance/repairs | F8: Home Depot | G8: 0.7 | H8: 84
A9: 46039 | B9: Mansfield, TX | C9: 360 County Road, Fairfield, TX | D9: 120 | E9: supplies | F9: Brookshire Brothers | G9: 0.7 | H9: 84
A10: 46040 | B10: Mansfield, TX | C10: 360 County Road, Fairfield, TX | D10: 120 | E10: maintenance/repairs, property work | F10: Ace Home Center, Pizza Hut | G10: 0.7 | H10: 84
A11: 46060 | B11: Mansfield, TX | C11: 360 County Road, Fairfield, TX | D11: 120 | E11: maintenance/repairs | F11: Capps True Value Hardware and Ag Center | G11: 0.7 | H11: 84
A12: 46063 | B12: Mansfield, TX | C12: 360 County Road, Fairfield, TX | D12: 120 | E12: maintenance/repairs, property work | F12: Exotic Smoke And Vape, Refund: Home Depot, Home Depot | G12: 0.7 | H12: 84
A13: 46067 | B13: Mansfield, TX | C13: 360 County Road, Fairfield, TX | D13: 120 | E13: property work | F13: Wendy's | G13: 0.7 | H13: 84
... A21: 46114 | B21: Mansfield, TX | C21: 360 County Road, Fairfield, TX | D21: 120 | E21: property work, supplies | F21: Burger King, Cooper Farms, Brookshire Brothers | G21: 0.7 | H21: 84
A22: TOTAL | D22: 2400 | H22: 1680
